xmapper/__init__.py
xmapper/utils.py
xmapper-1.0.4.dist-info/licenses/LICENSE
xmapper-1.0.4.dist-info/METADATA
xmapper-1.0.4.dist-info/WHEEL
xmapper-1.0.4.dist-info/top_level.txt
xmapper-1.0.4.dist-info/RECORD
