Metadata-Version: 2.4
Name: xmapper
Version: 1.0.4
Summary: Easy XML format converter
Home-page: https://github.com/xxh840912/xmapper
Author: Alex xi
Author-email: alexxi0213@gmail.com
Classifier: Programming Language :: Python :: 3
Classifier: License :: OSI Approved :: MIT License
Classifier: Operating System :: OS Independent
Requires-Python: >=3.8
License-File: LICENSE
Requires-Dist: lxml>=4.9.1
Requires-Dist: PyYAML>=6.0
Requires-Dist: untangle==1.2.1
Dynamic: author
Dynamic: author-email
Dynamic: classifier
Dynamic: description
Dynamic: description-content-type
Dynamic: home-page
Dynamic: license-file
Dynamic: requires-dist
Dynamic: requires-python
Dynamic: summary
